{
  "/tag/typescript": 117,
  "/tag/sql": 100,
  "/tag/nodejs": 98,
  "/tag/rust": 83,
  "/tag/go": 80,
  "/tag/python": 71,
  "/tag/kotlin": 68,
  "/tag/ruby": 60,
  "/tag/c": 59,
  "/tag/binary": 53,
  "/tag/dart": 49,
  "/tag/swift": 48,
  "/tag/java": 47,
  "/tag/php": 46,
  "/tag/lua": 46,
  "/tag/cpp": 45,
  "/tag/groovy": 44,
  "/tag/csharp": 43,
  "/tag/elixir": 42,
  "/tag/javascript": 41,
  "/tag/vue": 39,
  "/tag/markdown": 34,
  "/tag/container": 34,
  "/tag/shell": 33,
  "/tag/json": 33
}
