{
  "/tag/abap": "32",
  "/tag/binary": "57",
  "/tag/c": "74",
  "/tag/container": "35",
  "/tag/cpp": "44",
  "/tag/csharp": "45",
  "/tag/go": "133",
  "/tag/groovy": "33",
  "/tag/java": "42",
  "/tag/javascript": "57",
  "/tag/kotlin": "80",
  "/tag/lua": "34",
  "/tag/markdown": "32",
  "/tag/nodejs": "134",
  "/tag/php": "69",
  "/tag/plsql": "44",
  "/tag/python": "79",
  "/tag/ruby": "86",
  "/tag/rust": "83",
  "/tag/scala": "38",
  "/tag/shell": "35",
  "/tag/sql": "66",
  "/tag/swift": "74",
  "/tag/typescript": "112",
  "/tag/vue": "54"
}
