{
  "/tag/rust": 134,
  "/tag/typescript": 123,
  "/tag/nodejs": 120,
  "/tag/go": 117,
  "/tag/sql": 91,
  "/tag/c": 85,
  "/tag/binary": 78,
  "/tag/cpp": 75,
  "/tag/python": 72,
  "/tag/swift": 71,
  "/tag/lua": 70,
  "/tag/php": 69,
  "/tag/kotlin": 65,
  "/tag/ruby": 64,
  "/tag/csharp": 64,
  "/tag/vue": 59,
  "/tag/shell": 52,
  "/tag/javascript": 51,
  "/tag/java": 51,
  "/tag/delphi": 50,
  "/tag/powershell": 48,
  "/tag/groovy": 45,
  "/tag/elixir": 45,
  "/tag/plsql": 36,
  "/tag/perl": 36
}
