{
  "/tag/typescript": 137,
  "/tag/rust": 127,
  "/tag/nodejs": 120,
  "/tag/sql": 117,
  "/tag/php": 86,
  "/tag/cpp": 83,
  "/tag/go": 75,
  "/tag/c": 74,
  "/tag/binary": 71,
  "/tag/ruby": 69,
  "/tag/swift": 62,
  "/tag/python": 59,
  "/tag/csharp": 57,
  "/tag/vue": 51,
  "/tag/shell": 51,
  "/tag/groovy": 46,
  "/tag/security": 45,
  "/tag/javascript": 45,
  "/tag/kotlin": 44,
  "/tag/perl": 41,
  "/tag/plsql": 40,
  "/tag/lua": 40,
  "/tag/protobuf": 39,
  "/tag/verilog": 38,
  "/tag/markdown": 38
}
