{
  "better-code-hub": "21",
  "black": "25",
  "callgraph": "22",
  "cast-highlight": "25",
  "codacy": "23",
  "codescene": "37",
  "coverity": "30",
  "eslint": "23",
  "fortify": "34",
  "golangci-lint": "48",
  "hcl-appscan-source": "25",
  "lizard": "23",
  "mega-linter": "145",
  "mypy": "27",
  "nodejsscan": "40",
  "phpmetrics": "25",
  "security-code-scan": "24",
  "semgrep": "63",
  "sonarqube": "25",
  "sonatype": "32",
  "spoon": "25",
  "teamscale": "22",
  "trivy": "26",
  "veracode": "24",
  "wala": "25"
}
